curvewalk/__init__.py
curvewalk/boustrophedon.py
curvewalk/hilbert.py
curvewalk/lawnmower.py
curvewalk/zorder.py
curvewalk-0.4.0.dist-info/COPYING
curvewalk-0.4.0.dist-info/METADATA
curvewalk-0.4.0.dist-info/WHEEL
curvewalk-0.4.0.dist-info/RECORD
