Metadata-Version: 2.3
Name: curvewalk
Version: 0.4.0
Summary: 
License: MIT
Author: Mark Goodall
Author-email: mark.goodall@gmail.com
Requires-Python: >=3.12,<4.0
Classifier: License :: OSI Approved :: MIT License
Classifier: Programming Language :: Python :: 3
Classifier: Programming Language :: Python :: 3.12
Classifier: Programming Language :: Python :: 3.13
